dict8.py
dict8-0.4.0.dist-info/METADATA
dict8-0.4.0.dist-info/WHEEL
dict8-0.4.0.dist-info/top_level.txt
dict8-0.4.0.dist-info/RECORD
