Metadata-Version: 2.1
Name: dict8
Version: 0.4.0
Summary: traverse nested dicts and deal with it
Home-page: https://gitlab.com/diefans/dict8/
Author: Oliver Berger
Author-email: diefans@gmail.com
License: UNKNOWN
Project-URL: Bug Tracker, https://gitlab.com/diefans/dict8/-/issues
Platform: UNKNOWN
Classifier: Programming Language :: Python :: 3
Classifier: License :: OSI Approved :: The Unlicense (Unlicense)
Classifier: Operating System :: OS Independent
Requires-Python: >=3.8
Requires-Dist: attrs
Requires-Dist: typing-inspect
Provides-Extra: dev
Requires-Dist: flake8-annotations ; extra == 'dev'
Requires-Dist: flake8-typing-imports ; extra == 'dev'
Requires-Dist: pyflakes (<=2.4.0) ; extra == 'dev'
Provides-Extra: tests
Requires-Dist: pytest-mock ; extra == 'tests'
Requires-Dist: pytest-watch ; extra == 'tests'
Requires-Dist: pytest-cov ; extra == 'tests'
Requires-Dist: pdbpp ; extra == 'tests'
